emval-0.1.12.dist-info/METADATA
emval-0.1.12.dist-info/WHEEL
emval-0.1.12.dist-info/licenses/LICENSE
emval.libs/libgcc_s-0366c7ba.so.1
emval/__init__.py
emval/_emval.abi3.so
emval/model.py
emval/polars/__init__.py
emval/polars/plugin.py
emval/py.typed
emval/pyvenv.cfg
emval/validator.py
emval-0.1.12.dist-info/RECORD
