Metadata-Version: 2.4
Name: emval
Version: 0.1.12
Classifier: License :: OSI Approved :: MIT License
Classifier: Intended Audience :: Developers
Classifier: Programming Language :: Rust
Classifier: Programming Language :: Python :: Implementation :: CPython
Classifier: Programming Language :: Python :: Implementation :: PyPy
Classifier: Topic :: Software Development :: Libraries :: Python Modules
Classifier: Operating System :: POSIX :: Linux
Classifier: Operating System :: Microsoft :: Windows
Classifier: Operating System :: MacOS
Requires-Dist: pytest ; extra == 'tests'
Requires-Dist: polars>=1.32.2 ; extra == 'polars'
Provides-Extra: tests
Provides-Extra: polars
License-File: LICENSE
Summary: emval is a blazingly fast email validator
Home-Page: https://github.com/bnkc/emval
Author-email: Lev Ostatnigrosh <levostatnigrosh@gmail.com>
Requires-Python: >=3.10
Project-URL: Homepage, https://github.com/bnkc/emval
Project-URL: Issues, https://github.com/bnkc/emval/issues
